llama_index/llms/ollama/__init__.py
llama_index/llms/ollama/base.py
llama_index_llms_ollama-0.7.4.dist-info/METADATA
llama_index_llms_ollama-0.7.4.dist-info/WHEEL
llama_index_llms_ollama-0.7.4.dist-info/licenses/LICENSE
llama_index_llms_ollama-0.7.4.dist-info/RECORD
