Metadata-Version: 2.4
Name: llama-index-llms-ollama
Version: 0.7.4
Summary: llama-index llms ollama integration
Author-email: Your Name <you@example.com>
License-Expression: MIT
License-File: LICENSE
Requires-Python: <4.0,>=3.9
Requires-Dist: llama-index-core<0.15,>=0.13.0
Requires-Dist: ollama>=0.5.1
